hx/__init__.py
hx/client.py
hx/exceptions.py
hx/py.typed
hx/core/__init__.py
hx/core/auth.py
hx/core/base.py
hx/core/config.py
hx/core/http.py
hx/services/__init__.py
hx/services/knowledge/__init__.py
hx/services/knowledge/client.py
hx/services/knowledge/types.py
hx/services/memory/__init__.py
hx/services/memory/client.py
hx/services/memory/types.py
hx_sdk-0.1.3.dist-info/METADATA
hx_sdk-0.1.3.dist-info/WHEEL
hx_sdk-0.1.3.dist-info/RECORD
