Metadata-Version: 2.4
Name: hx-sdk
Version: 0.1.3
Summary: HexelStudio Python SDK
Project-URL: Homepage, https://hexelstudio.com
Project-URL: Documentation, https://docs.hexelstudio.com/sdk/python
Project-URL: Repository, https://github.com/hexelstudio/hx-python
Author-email: HexelStudio <support@hexelstudio.com>
License-Expression: MIT
Keywords: ai,hexelstudio,hx,knowledge,memory,sdk
Classifier: Development Status :: 4 - Beta
Classifier: Intended Audience :: Developers
Classifier: License :: OSI Approved :: MIT License
Classifier: Programming Language :: Python :: 3
Classifier: Programming Language :: Python :: 3.9
Classifier: Programming Language :: Python :: 3.10
Classifier: Programming Language :: Python :: 3.11
Classifier: Programming Language :: Python :: 3.12
Requires-Python: >=3.9
Requires-Dist: requests>=2.28.0
Provides-Extra: dev
Requires-Dist: pytest-cov>=4.0.0; extra == 'dev'
Requires-Dist: pytest>=7.0.0; extra == 'dev'
Requires-Dist: responses>=0.23.0; extra == 'dev'
